xmodits_py-0.3.5.dist-info/METADATA
xmodits_py-0.3.5.dist-info/WHEEL
xmodits_py-0.3.5.dist-info/licenses/LICENSE
xmodits/__init__.py
xmodits/xmodits.abi3.so
xmodits_py-0.3.5.dist-info/RECORD
