Metadata-Version: 2.3
Name: xmodits_py
Version: 0.3.5
Classifier: Programming Language :: Rust
Classifier: Programming Language :: Python :: Implementation :: CPython
Classifier: Programming Language :: Python :: Implementation :: PyPy
License-File: LICENSE
Summary: Extract samples from tracker modules. Supports IT, XM, S3M, MOD, UMX, MPTM
Author: B0ney - https://github.com/B0ney
License: LGPLv3
Requires-Python: >=3.7
Project-URL: Source Code, https://github.com/B0ney/xmodits-py
